popsims/__init__.py
popsims/abs_mag_relations.py
popsims/binaries.py
popsims/constants.py
popsims/core.py
popsims/core_tools.py
popsims/dynamics.py
popsims/evol_models.py
popsims/filterinitialize.py
popsims/fit.py
popsims/galaxy.py
popsims/plot_style.py
popsims/plot_tools.py
popsims/relations.py
popsims/simulator.py
popsims-0.2.4.dist-info/LICENSE
popsims-0.2.4.dist-info/METADATA
popsims-0.2.4.dist-info/WHEEL
popsims-0.2.4.dist-info/entry_points.txt
popsims-0.2.4.dist-info/top_level.txt
popsims-0.2.4.dist-info/zip-safe
popsims-0.2.4.dist-info/RECORD
