Metadata-Version: 2.1
Name: popsims
Version: 0.2.4
Summary: Population simulation code, https://github.com/caganze/popsims
Home-page: https://github.com/caganze/popsims
License-File: LICENSE
Requires-Dist: astropy
Requires-Dist: scipy
Requires-Dist: matplotlib
Requires-Dist: numpy
Requires-Dist: numba
Requires-Dist: pandas
Requires-Dist: tqdm
Requires-Dist: seaborn
